mildmouse/__init__.py
mildmouse/cache.py
mildmouse/cli.py
mildmouse/config.py
mildmouse/exceptions.py
mildmouse/formatter.py
mildmouse/search.py
mildmouse-0.1.0.dist-info/METADATA
mildmouse-0.1.0.dist-info/WHEEL
mildmouse-0.1.0.dist-info/entry_points.txt
mildmouse-0.1.0.dist-info/RECORD
