Metadata-Version: 2.4
Name: mildmouse
Version: 0.1.0
Summary: Google Custom Search API client
Author-email: Taylor Monacelli <taylormonacelli@gmail.com>
Requires-Python: >=3.12
Requires-Dist: platformdirs>=3.0.0
Requires-Dist: python-dotenv>=1.0.0
